README.md
setup.cfg
setup.py
reporeleaser/__init__.py
reporeleaser/cli.py
reporeleaser/const.py
reporeleaser/messages.py
reporeleaser/release.py
reporeleaser/version.py
reporeleaser.egg-info/PKG-INFO
reporeleaser.egg-info/SOURCES.txt
reporeleaser.egg-info/dependency_links.txt
reporeleaser.egg-info/entry_points.txt
reporeleaser.egg-info/requires.txt
reporeleaser.egg-info/top_level.txt